loggex/__init__.py
loggex/core.py
loggex-0.1.0.dist-info/LICENSE
loggex-0.1.0.dist-info/METADATA
loggex-0.1.0.dist-info/WHEEL
loggex-0.1.0.dist-info/top_level.txt
loggex-0.1.0.dist-info/RECORD
