Metadata-Version: 2.1
Name: loggex
Version: 0.1.0
Summary: A flexible experiment logging library for research and machine learning projects
Home-page: https://github.com/nsuruguay05/loggex
Author: Ignacio Sastre
Author-email: isastre@fing.edu.uy
License: MIT
Requires-Python: >=3.7
License-File: LICENSE
Requires-Dist: pandas
Requires-Dist: openpyxl
